<?xml version="1.0" encoding="utf-8"?>
<FlightState xmlVersion="3" time="32116510960.447224" totalFlightTimeInRealtimeSeconds="53029.724381776527" playerNodeId="458" minNodeId="458">
  <PlanetarySystem hash="95b3794d-038b-2f48-4646-497456d62794" />
  <Nodes>
    <Planet name="Juno" rotation="0" trueAnomaly="0" />
    <Planet name="Vulco" rotation="-5.2151882926013062" trueAnomaly="5.2151707701878465" />
    <Planet name="Sergeaa" rotation="-1.5899269761751658" trueAnomaly="5.2706215220699972" />
    <Planet name="Droo" rotation="-0.26407287155081161" trueAnomaly="3.6921809350551458" />
    <Planet name="Brigo" rotation="-0.89430100922548361" trueAnomaly="4.6971470299825349" />
    <Planet name="Luna" rotation="-0.22357293529778405" trueAnomaly="0.24970560696028016" />
    <Planet name="T.T." rotation="0.093697888265822149" trueAnomaly="0.025795336163796638" />
    <Planet name="Cylero" rotation="-2.2640728713300957" trueAnomaly="2.5485372371171784" />
    <Planet name="Niobe" rotation="1.2753766384930483" trueAnomaly="5.53163810389891" />
    <Planet name="Herma" rotation="-1.913064958195311" trueAnomaly="3.97295667508496" />
    <Planet name="Handrew's Comet" rotation="6.1630649580707226" trueAnomaly="2.8042480517360739" />
    <Planet name="Tydos" rotation="-1.4830443490591392" trueAnomaly="0.80704347168258772" />
    <Planet name="Nebra" rotation="-4.7472581784711716" trueAnomaly="4.028394518757" />
    <Planet name="Miros" rotation="-3.696250265347115" trueAnomaly="6.1709225325393655" />
    <Planet name="Orcus" rotation="-1.1320364361650321" trueAnomaly="3.4266033551999633" />
    <Planet name="Urados" rotation="0" trueAnomaly="4.6780411187539341" />
    <Planet name="Jastrus" rotation="-3.2637837643330219" trueAnomaly="5.0637464753266883" />
    <Planet name="Boreas" rotation="-2.0490625659389656" trueAnomaly="3.3418175547411986" />
    <Planet name="Taurus" rotation="4.098125132596186" trueAnomaly="2.3883546295316664" />
    <Planet name="Hypatchion" rotation="-3.9621275244420269" trueAnomaly="2.3446783856051261" />
    <Craft id="112" name="New-112" parent="Droo" position="1146871.14625479,-549477.312332216,-77415.4562848856" velocity="9.65215587047646,1E-09,142.991846825354" heading="0.709281580647528,-0.474344128993614,-0.047965851699416,0.519245483060913" inContactWithPlanet="true" hasCommandPod="false" craftMass="4.46768761" craftPartCount="1" allowPlayerControl="true" waterDepth="0" initialNodes="110" surfacePosition="1086908.20611571,-549477.312332216,-374081.716289234" surfaceVelocity="46.6404928317135,0,135.515669942218" surfaceRotation="0.696793050687149,-0.401855092609592,-0.140927480501338,0.577174787249803">
      <InitialCrafts>
        <InitialCraft nodeId="110" name="New" launchPlanetName="Droo" launchLocationName="DSC Bay" launchLocationType="SurfaceLockedGround" launchTime="10511.111068710685" launchMass="29061.8867" launchPrice="24812718" initialCrewCount="1" />
      </InitialCrafts>
      <Orbit argumentOfPeriapsis="1.5707963268080609" eccentricity="0.9983549672737414" inclination="0.44591120126200717" prograde="true" rightAscensionOfAscendingNode="1.5033971274944535" semiMajorAxis="637554.99046545825" time="32116510960.447224" trueAnomaly="3.1415926535897931" />
    </Craft>
    <Craft id="145" name="New" parent="Droo" position="1168683.83364139,-6640.15436478498,-507660.72279879" velocity="63.2882267105488,1E-09,145.695587810453" heading="-0.186050016655106,-0.396421188523949,0.653830608164893,-0.617042215198515" inContactWithPlanet="true" hasCommandPod="true" craftMass="22.8160324" craftPartCount="10" allowPlayerControl="true" waterDepth="0" initialNodes="145" surfacePosition="995664.548502518,-6640.15436478498,-795105.917059229" surfaceVelocity="99.1229797340216,0,124.125899135709" surfaceRotation="-0.0983517775424484,-0.474206218409049,0.672633648513417,-0.559481317701459">
      <InitialCrafts>
        <InitialCraft nodeId="145" name="New" launchPlanetName="Droo" launchLocationName="DSC Launch Pad" launchLocationType="SurfaceLockedGround" launchTime="1490171847.9412487" launchMass="54784.72" launchPrice="8510485" initialCrewCount="1" />
      </InitialCrafts>
      <Orbit argumentOfPeriapsis="1.5707963280028954" eccentricity="0.99797890371577158" inclination="0.0052112579672550421" prograde="true" rightAscensionOfAscendingNode="1.1610019929298847" semiMajorAxis="637744.425167372" time="32116510960.447224" trueAnomaly="3.1415926746632175" />
    </Craft>
    <Craft id="168" name="New-168" parent="Juno" position="-2839401180350.47,-2171402679556.5,36232177008574.5" velocity="-95.2731041275082,-71.3605743705651,1193.26781374619" heading="0.619576334953308,-0.301154166460037,0.280604600906372,0.668350696563721" inContactWithPlanet="false" hasCommandPod="false" craftMass="190.661346" craftPartCount="6" allowPlayerControl="true" waterDepth="0" initialNodes="167">
      <InitialCrafts>
        <InitialCraft nodeId="167" name="New" launchPlanetName="Droo" launchLocationName="DSC Launch Pad" launchLocationType="SurfaceLockedGround" launchTime="1681838246.658006" launchMass="293079.031" launchPrice="31481806" initialCrewCount="0" />
      </InitialCrafts>
      <Orbit argumentOfPeriapsis="3.112222633007812" eccentricity="1.173506591209813" inclination="0.10878410078103587" prograde="true" rightAscensionOfAscendingNode="2.2278485983156706" semiMajorAxis="-87339859421.869339" time="32116510960.447224" trueAnomaly="2.5893992006222426" />
    </Craft>
    <Craft id="204" name="New-204" parent="Droo" position="1160874.61657083,-6.55380378007257,-525000.986063013" velocity="65.4566169112667,1E-09,144.736728265441" heading="0.680225580903334,-0.697250919634511,-0.210670365076378,0.0821743925992301" inContactWithPlanet="true" hasCommandPod="false" craftMass="30.1719227" craftPartCount="8" allowPlayerControl="true" waterDepth="0" initialNodes="202" surfacePosition="983599.980391986,-6.55380378007257,-809806.760491969" surfaceVelocity="100.965926352212,0,122.634297495815" surfaceRotation="0.646569401986751,-0.680363445087713,-0.298390480432212,0.173254391955231">
      <InitialCrafts>
        <InitialCraft nodeId="202" name="New" launchPlanetName="Droo" launchLocationName="DSC Launch Pad" launchLocationType="SurfaceLockedGround" launchTime="1684767225.4226124" launchMass="132962.125" launchPrice="24034917" initialCrewCount="1" />
      </InitialCrafts>
      <Orbit argumentOfPeriapsis="1.5707975506024496" eccentricity="0.997979053925921" inclination="5.143987896541406E-06" prograde="true" rightAscensionOfAscendingNode="1.1460749118699169" semiMajorAxis="637679.66144467262" time="32116510960.447224" trueAnomaly="3.1415926746632175" />
    </Craft>
    <Craft id="244" name="New-244" parent="Droo" position="1187873.91810043,-1023.7613561546,-460881.628994569" velocity="57.4587118513797,1E-09,148.09378565338" heading="-0.438501201589371,0.574157906421655,0.555018017366649,0.4123305228714" inContactWithPlanet="true" hasCommandPod="false" craftMass="18.0925179" craftPartCount="9" allowPlayerControl="true" waterDepth="0" initialNodes="242" surfacePosition="1026399.42362982,-1023.7613561546,-754957.312978906" surfaceVelocity="94.1215096839064,0,127.962550504401" surfaceRotation="-0.361614580979147,0.623444961537292,0.60791711986487,0.333151869125353">
      <InitialCrafts>
        <InitialCraft nodeId="242" name="New" launchPlanetName="Droo" launchLocationName="DSC Launch Pad" launchLocationType="SurfaceLockedGround" launchTime="2009691518.1398618" launchMass="190830.375" launchPrice="78178799" initialCrewCount="1" />
      </InitialCrafts>
      <Orbit argumentOfPeriapsis="1.5707963346298179" eccentricity="0.9979789298270757" inclination="0.00080348603799774792" prograde="true" rightAscensionOfAscendingNode="1.2006872220192957" semiMajorAxis="637719.27029912721" time="32116510960.447224" trueAnomaly="3.1415926535897931" />
    </Craft>
    <Craft id="245" name="Unassigned" parent="Droo" position="1187851.63531577,-838.645010830465,-461076.377935902" velocity="57.480756155336,1E-09,148.085248921155" heading="0.707004578248672,0.650598787935763,0.0222821615337661,-0.276353787243268" inContactWithPlanet="true" hasCommandPod="true" craftMass="1.16126" craftPartCount="1" allowPlayerControl="true" waterDepth="0" initialNodes="242" surfacePosition="1026327.08100358,-838.645010830465,-755139.494803113" surfaceVelocity="94.1405616101106,0,127.948555818199" surfaceRotation="0.703784237379284,0.608553057212425,-0.0709911403592206,-0.35960172623807">
      <InitialCrafts>
        <InitialCraft nodeId="242" name="New" launchPlanetName="Droo" launchLocationName="DSC Launch Pad" launchLocationType="SurfaceLockedGround" launchTime="2009691518.1398618" launchMass="190830.375" launchPrice="78178799" initialCrewCount="1" />
      </InitialCrafts>
      <Orbit argumentOfPeriapsis="1.5707963363596138" eccentricity="0.99797885080283255" inclination="0.00065817421806477281" prograde="true" rightAscensionOfAscendingNode="1.2005384035391138" semiMajorAxis="637744.09501815145" time="32116510960.447224" trueAnomaly="3.1415926746632175" />
    </Craft>
    <Craft id="261" name="New" parent="Juno" position="5423871787.71975,-44165552.8228813,-5630502165.63486" velocity="2842.60736999856,1.33393943475127,3390.51415380074" heading="-0.591792702674866,-0.619695544242859,0.387017548084259,-0.340553402900696" inContactWithPlanet="false" hasCommandPod="true" craftMass="35.731102" craftPartCount="22" allowPlayerControl="true" waterDepth="0" initialNodes="261">
      <InitialCrafts>
        <InitialCraft nodeId="261" name="New" launchPlanetName="Droo" launchLocationName="DSC Launch Pad" launchLocationType="SurfaceLockedGround" launchTime="2009692942.4628973" launchMass="1267127" launchPrice="199481038" initialCrewCount="1" />
      </InitialCrafts>
      <Orbit argumentOfPeriapsis="5.2098472507263871" eccentricity="0.24708293008864204" inclination="0.00565712003348759" prograde="true" rightAscensionOfAscendingNode="0.81975653637869017" semiMajorAxis="10079815107.414774" time="32116510960.447224" trueAnomaly="5.7326795049310117" />
    </Craft>
    <Craft id="262" name="New-262" parent="Juno" position="3504451781.7907,52393175.6056906,9985471981.27297" velocity="-4035.17935088235,3.01032683264356,1609.04373892816" heading="0.477786332368851,-0.512530326843262,0.481138557195663,0.526819229125977" inContactWithPlanet="false" hasCommandPod="false" craftMass="1068.8877" craftPartCount="22" allowPlayerControl="true" waterDepth="0" initialNodes="261">
      <InitialCrafts>
        <InitialCraft nodeId="261" name="New" launchPlanetName="Droo" launchLocationName="DSC Launch Pad" launchLocationType="SurfaceLockedGround" launchTime="2009692942.4628973" launchMass="1267127" launchPrice="199481038" initialCrewCount="1" />
      </InitialCrafts>
      <Orbit argumentOfPeriapsis="1.3610000966366997" eccentricity="0.59865193000966077" inclination="0.0049746454417910662" prograde="true" rightAscensionOfAscendingNode="6.0435052584696729" semiMajorAxis="26306077620.776516" time="32116510960.447224" trueAnomaly="0.11195209517211106" />
    </Craft>
    <Craft id="265" name="New-265" parent="Juno" position="-10849423043027.5,-1771817317467.17,49318306191371.3" velocity="-462.001109026301,-75.313060883646,2096.42495589357" heading="0.774673223495483,-0.510730564594269,0.168568938970566,-0.332595944404602" inContactWithPlanet="false" hasCommandPod="false" craftMass="1283.69263" craftPartCount="29" allowPlayerControl="true" waterDepth="0" initialNodes="264">
      <InitialCrafts>
        <InitialCraft nodeId="264" name="New" launchPlanetName="Droo" launchLocationName="DSC Launch Pad" launchLocationType="SurfaceLockedGround" launchTime="2353342958.5157046" launchMass="2372942.5" launchPrice="201146779" initialCrewCount="1" />
      </InitialCrafts>
      <Orbit argumentOfPeriapsis="2.5051835253854309" eccentricity="1.214600066184764" inclination="0.037079785191792738" prograde="true" rightAscensionOfAscendingNode="3.0274699143580994" semiMajorAxis="-27119867924.240425" time="32116510960.447224" trueAnomaly="2.5376557161327038" />
    </Craft>
    <Craft id="269" name="New-269" parent="Juno" position="51001055531630.6,13386748729218.6,-26687860092870" velocity="1763.36950880395,462.670609077021,-921.504263294093" heading="-0.00354659510776401,-0.700067341327667,0.677983343601227,0.224124222993851" inContactWithPlanet="false" hasCommandPod="false" craftMass="2331.63647" craftPartCount="53" allowPlayerControl="true" waterDepth="0" initialNodes="268">
      <InitialCrafts>
        <InitialCraft nodeId="268" name="New" launchPlanetName="Droo" launchLocationName="DSC Launch Pad" launchLocationType="SurfaceLockedGround" launchTime="3234779372.5691833" launchMass="4048031.25" launchPrice="371231317" initialCrewCount="1" />
      </InitialCrafts>
      <Orbit argumentOfPeriapsis="5.6974264359843172" eccentricity="1.45372019168655" inclination="0.23199778222059703" prograde="true" rightAscensionOfAscendingNode="4.0533609919840279" semiMajorAxis="-29986978805.287785" time="32116510960.447224" trueAnomaly="2.3288394269795396" />
    </Craft>
    <Craft id="271" name="New-271" parent="Juno" position="66378342171.2681,23788726619.2313,-511805583361.407" velocity="109.346032681818,-25.6296680811297,525.687185431987" heading="-0.0718294754624367,0.700580835342407,0.703563749790192,-0.0950006395578384" inContactWithPlanet="false" hasCommandPod="false" craftMass="3342.73" craftPartCount="71" allowPlayerControl="true" waterDepth="0" initialNodes="270">
      <InitialCrafts>
        <InitialCraft nodeId="270" name="New" launchPlanetName="Droo" launchLocationName="DSC Launch Pad" launchLocationType="SurfaceLockedGround" launchTime="18960096752.563046" launchMass="5652862" launchPrice="541166263" initialCrewCount="1" />
      </InitialCrafts>
      <Orbit argumentOfPeriapsis="4.58141567590301" eccentricity="0.94698128019200112" inclination="0.047793773925793773" prograde="true" rightAscensionOfAscendingNode="3.0003011594661282" semiMajorAxis="641237930405.40112" time="32116510960.447224" trueAnomaly="3.5425381380277461" />
    </Craft>
    <Craft id="273" name="New-273" parent="Juno" position="19527111342825.4,1881633468377.15,5120720154343.76" velocity="1633.09538893136,156.735815588574,437.661393980775" heading="-0.0612761303782463,0.700638115406036,0.704350531101227,-0.0961346700787544" inContactWithPlanet="false" hasCommandPod="false" craftMass="3352.49951" craftPartCount="71" allowPlayerControl="true" waterDepth="0" initialNodes="272">
      <InitialCrafts>
        <InitialCraft nodeId="272" name="New" launchPlanetName="Droo" launchLocationName="DSC Launch Pad" launchLocationType="SurfaceLockedGround" launchTime="18960097021.475609" launchMass="5701996.5" launchPrice="543098386" initialCrewCount="1" />
      </InitialCrafts>
      <Orbit argumentOfPeriapsis="0.40967131386811784" eccentricity="2.7026058436534885" inclination="0.13135170537162691" prograde="true" rightAscensionOfAscendingNode="4.18121675396015" semiMajorAxis="-43542118204.727211" time="32116510960.447224" trueAnomaly="1.9444332190674336" />
    </Craft>
    <Craft id="275" name="New-275" parent="Juno" position="-25743170269.3009,25722697.8793075,-3492558056.45439" velocity="-419.322598982043,-2.40457139213153,-2088.6999476769" heading="0.69829273223877,-0.00411157077178359,-0.115789383649826,0.706373333930969" inContactWithPlanet="false" hasCommandPod="false" craftMass="190.757172" craftPartCount="5" allowPlayerControl="true" waterDepth="0" initialNodes="274">
      <InitialCrafts>
        <InitialCraft nodeId="274" name="New" launchPlanetName="Droo" launchLocationName="DSC Launch Pad" launchLocationType="SurfaceLockedGround" launchTime="18960097183.7398" launchMass="368278.7" launchPrice="32446663" initialCrewCount="1" />
      </InitialCrafts>
      <Orbit argumentOfPeriapsis="0.50281396286029045" eccentricity="0.33122141102816011" inclination="0.0018280929448827397" prograde="true" rightAscensionOfAscendingNode="0.70720983849915164" semiMajorAxis="24583818784.409073" time="32116510960.447224" trueAnomaly="2.06641408765391" />
    </Craft>
    <Craft id="288" name="New Airplane" parent="Droo" position="1250690.21957572,5722.35003051747,-239541.829928313" velocity="29.880729599074,1E-09,156.012568971909" heading="0.570569707462123,-0.417271288380478,0.546733078537268,-0.448796234138514" inContactWithPlanet="true" hasCommandPod="true" craftMass="186.058685" craftPartCount="25" allowPlayerControl="true" waterDepth="0" initialNodes="288" surfacePosition="1144811.06519311,5722.35003051747,-557686.23673099" surfaceVelocity="69.5664370847915,0,142.805078725917" surfaceRotation="0.637582509851168,-0.472724728853217,0.466856965598764,-0.38995479024224">
      <InitialCrafts>
        <InitialCraft nodeId="288" name="New Airplane" launchPlanetName="Droo" launchLocationName="DSC Eastward Runway" launchLocationType="SurfaceLockedGround" launchTime="20737977542.384178" launchMass="22822" launchPrice="9222421" initialCrewCount="1" />
      </InitialCrafts>
      <Orbit argumentOfPeriapsis="4.7123889789837765" eccentricity="0.99798010145122351" inclination="0.00449364523952512" prograde="true" rightAscensionOfAscendingNode="4.5231529709638236" semiMajorAxis="637361.6662055885" time="32116510960.447224" trueAnomaly="3.1415926325163688" />
    </Craft>
    <Craft id="295" name="New Airplane" parent="Droo" position="1127262.30143573,9776.60845647564,-593861.210257037" velocity="74.0367731349292,1E-09,140.535973445432" heading="0.591478310067088,0.611504431773855,0.369558877079562,0.373687029468343" inContactWithPlanet="true" hasCommandPod="true" craftMass="149.970963" craftPartCount="27" allowPlayerControl="true" waterDepth="0" initialNodes="295" surfacePosition="933179.329717507,9776.60845647564,-867506.640824211" surfaceVelocity="108.152193223645,0,116.339617969991" surfaceRotation="0.634983585800352,0.655378881744682,0.288472228026999,0.289927947150597">
      <InitialCrafts>
        <InitialCraft nodeId="295" name="New Airplane" launchPlanetName="Droo" launchLocationName="DSC Westward Runway" launchLocationType="SurfaceLockedGround" launchTime="20737980014.39909" launchMass="17641.0117" launchPrice="17465058" initialCrewCount="1" />
      </InitialCrafts>
      <Orbit argumentOfPeriapsis="4.7123889795642695" eccentricity="0.99797902905970826" inclination="0.0076730508142792706" prograde="true" rightAscensionOfAscendingNode="4.2275184601935294" semiMajorAxis="637725.06130826846" time="32116510960.447224" trueAnomaly="3.1415926535897931" />
    </Craft>
    <Craft id="314" name="New Airplane" parent="Droo" position="-568532.165800856,-23166.2323331082,-1140096.77454914" velocity="142.131709731049,1E-09,-70.8768330603579" heading="0.35014368979023,0.347724557710717,-0.623732162836813,-0.606172983103959" inContactWithPlanet="true" hasCommandPod="true" craftMass="26.9413414" craftPartCount="13" allowPlayerControl="true" waterDepth="0" initialNodes="314" surfacePosition="-846405.612167369,-23166.2323331082,-952180.139773536" surfaceVelocity="118.704827747172,0,-105.518302892206" surfaceRotation="0.26497971277901,0.264893357841007,-0.66440062708749,-0.646675798391167">
      <InitialCrafts>
        <InitialCraft nodeId="314" name="New Airplane" launchPlanetName="Droo" launchLocationName="DSC Westward Runway" launchLocationType="SurfaceLockedGround" launchTime="20738354972.683659" launchMass="25169.11" launchPrice="17474314" initialCrewCount="1" />
      </InitialCrafts>
      <Orbit argumentOfPeriapsis="1.5707963271410934" eccentricity="0.99797951645027683" inclination="0.018182000567266845" prograde="true" rightAscensionOfAscendingNode="5.8206021884523755" semiMajorAxis="637744.37670323544" time="32116510960.447224" trueAnomaly="3.1415926535897931" />
    </Craft>
    <Craft id="335" name="New" parent="Juno" position="3260845087240.43,2823675516116.26,72937035593714.2" velocity="285.057949046856,248.132736497031,6410.15609713676" heading="-0.360012084245682,-0.589864671230316,0.376570165157318,0.616965234279633" inContactWithPlanet="false" hasCommandPod="true" craftMass="7.22065" craftPartCount="8" allowPlayerControl="true" waterDepth="0" initialNodes="335">
      <InitialCrafts>
        <InitialCraft nodeId="335" name="New" launchPlanetName="Droo" launchLocationName="DSC Large Pad" launchLocationType="SurfaceLockedGround" launchTime="20738412230.346638" launchMass="235237.859" launchPrice="117712500" initialCrewCount="0" />
      </InitialCrafts>
      <Orbit argumentOfPeriapsis="0.25126662813678641" eccentricity="5.806318273515279" inclination="0.042415915875490706" prograde="true" rightAscensionOfAscendingNode="5.8140513278048394" semiMajorAxis="-3031809200.5256677" time="32116510960.447224" trueAnomaly="1.7436481701686113" />
    </Craft>
    <Craft id="351" name="New" parent="Droo" position="1149543.47500844,14259.1714102978,-550187.730831446" velocity="68.5735577619634,1E-09,143.275252183929" heading="-0.866621013832806,0.276549279034229,0.227882476866804,-0.347215642853348" inContactWithPlanet="true" hasCommandPod="true" craftMass="149.984039" craftPartCount="11" allowPlayerControl="true" waterDepth="0" initialNodes="351" surfacePosition="966087.531029196,14259.1714102978,-831162.813461864" surfaceVelocity="103.593351877169,0,120.409917196861" surfaceRotation="-0.829076397468749,0.228430138285558,0.339992315230447,-0.380602008268291">
      <InitialCrafts>
        <InitialCraft nodeId="351" name="New" launchPlanetName="Droo" launchLocationName="DSC Westward Runway" launchLocationType="SurfaceLockedGround" launchTime="29658888239.38937" launchMass="15090.3535" launchPrice="1611229" initialCrewCount="0" />
      </InitialCrafts>
      <Orbit argumentOfPeriapsis="4.7123889798220473" eccentricity="0.99797861976122193" inclination="0.011188250941363937" prograde="true" rightAscensionOfAscendingNode="4.2659959855918412" semiMajorAxis="637896.64090991777" time="32116510960.447224" trueAnomaly="3.1415926535897931" />
    </Craft>
    <Craft id="352" name="New" parent="Droo" position="1147577.41995048,11696.3802117783,-554024.392821435" velocity="69.0591081970374,1E-09,143.045458351109" heading="-0.219820121870371,-0.272669690176819,-0.31079731450987,-0.883592664713466" inContactWithPlanet="true" hasCommandPod="true" craftMass="149.878387" craftPartCount="11" allowPlayerControl="true" waterDepth="0" initialNodes="352" surfacePosition="963188.205454763,11696.3802117783,-834353.308553507" surfaceVelocity="104.002091165188,0,120.061353536918" surfaceRotation="-0.2588242144949,-0.386624065705678,-0.279152091743223,-0.840003948812432">
      <InitialCrafts>
        <InitialCraft nodeId="352" name="New" launchPlanetName="Droo" launchLocationName="DSC Westward Runway" launchLocationType="SurfaceLockedGround" launchTime="29658889348.028484" launchMass="15079.7881" launchPrice="1610173" initialCrewCount="0" />
      </InitialCrafts>
      <Orbit argumentOfPeriapsis="4.7123889796988259" eccentricity="0.99797875249884849" inclination="0.00917830999103725" prograde="true" rightAscensionOfAscendingNode="4.2626141737518424" semiMajorAxis="637828.59855241294" time="32116510960.447224" trueAnomaly="3.1415926535897931" />
    </Craft>
    <Craft id="354" name="New" parent="Droo" position="1151514.700075,-5104.28733514717,-545642.204688198" velocity="68.0200532280573,1E-09,143.548447167408" heading="-0.631662541799941,0.375078185293275,0.351120221744446,0.580546193970717" inContactWithPlanet="true" hasCommandPod="true" craftMass="160.353729" craftPartCount="16" allowPlayerControl="true" waterDepth="0" initialNodes="354" surfacePosition="969176.87113868,-5104.28733514717,-827289.376503563" surfaceVelocity="103.130342450205,0,120.818114500374" surfaceRotation="-0.5799384005357,0.448244172479836,0.431224368488571,0.526112835298636">
      <InitialCrafts>
        <InitialCraft nodeId="354" name="New" launchPlanetName="Droo" launchLocationName="DSC Westward Runway" launchLocationType="SurfaceLockedGround" launchTime="29658893335.332188" launchMass="16127.3223" launchPrice="2418336" initialCrewCount="0" />
      </InitialCrafts>
      <Orbit argumentOfPeriapsis="1.5707963283664617" eccentricity="0.99797878654601313" inclination="0.0040056993989103437" prograde="true" rightAscensionOfAscendingNode="1.1282888567399756" semiMajorAxis="637774.34798938991" time="32116510960.447224" trueAnomaly="3.1415926746632175" />
    </Craft>
    <Craft id="355" name="New" parent="Droo" position="1153712.37009901,-26720.8043406072,-539656.455966871" velocity="67.2892480600242,1E-09,143.855293498567" heading="-0.213865154607317,-0.465807306530621,0.680592092059795,-0.523526775112205" inContactWithPlanet="true" hasCommandPod="true" craftMass="294.948242" craftPartCount="12" allowPlayerControl="true" waterDepth="0" initialNodes="355" surfacePosition="972860.725289811,-26720.8043406072,-822084.747805712" surfaceVelocity="102.504962017645,0,121.305074641597" surfaceRotation="-0.122401576311632,-0.530676791907888,0.702824146643559,-0.457644949193522">
      <InitialCrafts>
        <InitialCraft nodeId="355" name="New" launchPlanetName="Droo" launchLocationName="DSC Westward Runway" launchLocationType="SurfaceLockedGround" launchTime="29658936732.240093" launchMass="29586.7734" launchPrice="30710851" initialCrewCount="0" />
      </InitialCrafts>
      <Orbit argumentOfPeriapsis="1.5707963270949692" eccentricity="0.997980105146351" inclination="0.020976003209244105" prograde="true" rightAscensionOfAscendingNode="1.1332746074326445" semiMajorAxis="637628.13961321558" time="32116510960.447224" trueAnomaly="3.1415926746632175" />
    </Craft>
    <Craft id="356" name="New" parent="Droo" position="1143064.36661441,-44649.3257049307,-560977.166133841" velocity="69.9414637572527,1E-09,142.514882594516" heading="-0.374355429859699,-0.579674743015906,0.608204270849539,-0.392330945632547" inContactWithPlanet="true" hasCommandPod="true" craftMass="295.5954" craftPartCount="14" allowPlayerControl="true" waterDepth="0" initialNodes="356" surfacePosition="957016.823628677,-44649.3257049307,-839887.09148244" surfaceVelocity="104.715371882156,0,119.318862737697" surfaceRotation="-0.291025006167,-0.626280772246116,0.652195442830171,-0.312600062000933">
      <InitialCrafts>
        <InitialCraft nodeId="356" name="New" launchPlanetName="Droo" launchLocationName="DSC Secondary Runway" launchLocationType="SurfaceLockedGround" launchTime="29658941079.575768" launchMass="29651.4883" launchPrice="30714565" initialCrewCount="0" />
      </InitialCrafts>
      <Orbit argumentOfPeriapsis="1.5707963269744227" eccentricity="0.99798151771580823" inclination="0.035051486278676873" prograde="true" rightAscensionOfAscendingNode="1.1145631406318841" semiMajorAxis="637684.60632759542" time="32116510960.447224" trueAnomaly="3.1415926535897931" />
    </Craft>
    <Craft id="376" name="New" parent="Droo" position="-246011.30442869,-349701.760548246,1200321.02308397" velocity="-149.639772259956,1E-09,-30.6693583300745" heading="0.168973044050372,0.0189141854074991,-0.653994846928353,0.737144876413394" inContactWithPlanet="true" hasCommandPod="true" craftMass="24.7681751" craftPartCount="3" allowPlayerControl="true" waterDepth="0" initialNodes="376" surfacePosition="75817.7605233913,-349701.760548246,1222924.27711338" surfaceVelocity="-152.457639913898,0,9.45193177474362" surfaceRotation="0.0814018225120971,0.115796973255899,-0.670548221081205,0.728238563186929">
      <InitialCrafts>
        <InitialCraft nodeId="376" name="New" launchPlanetName="Droo" launchLocationName="DSC Large Pad" launchLocationType="SurfaceLockedGround" launchTime="31031796139.648964" launchMass="304703.2" launchPrice="167105254" initialCrewCount="0" />
      </InitialCrafts>
      <Orbit argumentOfPeriapsis="1.5707963268169503" eccentricity="0.99813108681840124" inclination="0.27801590352355476" prograde="true" rightAscensionOfAscendingNode="3.34374767247017" semiMajorAxis="637695.46742140932" time="32116510960.447224" trueAnomaly="3.1415926535897931" />
    </Craft>
    <Craft id="380" name="New" parent="Juno" position="2763323772094.85,-293340835.899366,-3607244986200.92" velocity="2536.10344052891,-0.270130721215248,-3322.85882854316" heading="0.00392434420064092,-0.439570486545563,0.00801844801753759,-0.898163795471191" inContactWithPlanet="false" hasCommandPod="true" craftMass="11778.5059" craftPartCount="13" allowPlayerControl="true" waterDepth="0" initialNodes="380">
      <InitialCrafts>
        <InitialCraft nodeId="380" name="New" launchPlanetName="Droo" launchLocationName="DSC Launch Pad" launchLocationType="SurfaceLockedGround" launchTime="31032585887.431717" launchMass="15041731" launchPrice="3408838160" initialCrewCount="0" />
      </InitialCrafts>
      <Orbit argumentOfPeriapsis="1.8840740900454738" eccentricity="1.5075395063506867" inclination="3.141517655599904" prograde="false" rightAscensionOfAscendingNode="3.2612503111049866" semiMajorAxis="-7176404067.5631886" time="32116510960.447224" trueAnomaly="2.2942794156215824" />
    </Craft>
    <Craft id="411" name="New" parent="Juno" position="-4831378359.4942,-7951342.7822808,-12458689217.708" velocity="1504.57312362305,-2.17122713063843,-3062.2275739773" heading="0.670330345630646,-0.648063600063324,-0.259887903928757,0.251254975795746" inContactWithPlanet="false" hasCommandPod="true" craftMass="183270.563" craftPartCount="199" allowPlayerControl="true" waterDepth="0" initialNodes="411">
      <InitialCrafts>
        <InitialCraft nodeId="411" name="New" launchPlanetName="Droo" launchLocationName="DSC Launch Pad" launchLocationType="SurfaceLockedGround" launchTime="31439620291.790749" launchMass="193521008" launchPrice="37579763283" initialCrewCount="0" />
      </InitialCrafts>
      <Orbit argumentOfPeriapsis="2.1672194856587259" eccentricity="0.7008228682192571" inclination="0.0006742846330809319" prograde="true" rightAscensionOfAscendingNode="0.11975448042706001" semiMajorAxis="17685744863.983818" time="32116510960.447224" trueAnomaly="2.0554770813913579" />
    </Craft>
    <Craft id="443" name="Airplane-443" parent="Droo" position="589755.31674731,552060.773600342,-988542.66660824" velocity="123.002892181247,1E-09,73.3823759859366" heading="0.354674883811073,0.891296947086192,0.233159318091475,0.15947484167516" inContactWithPlanet="true" hasCommandPod="false" craftMass="58.0941925" craftPartCount="9" allowPlayerControl="true" waterDepth="0" initialNodes="441" surfacePosition="311287.533275935,552060.773600342,-1108209.37054495" surfaceVelocity="137.892841982316,0,38.7330442946679" surfaceRotation="0.382283899529248,0.904534345956345,0.184435816716066,0.0407447329678009">
      <InitialCrafts>
        <InitialCraft nodeId="441" name="Airplane" launchPlanetName="Droo" launchLocationName="Juno Village Runway" launchLocationType="SurfaceLockedGround" launchTime="32116319013.622425" launchMass="28712.4355" launchPrice="28580974" initialCrewCount="2" />
      </InitialCrafts>
      <Orbit argumentOfPeriapsis="4.7123889803715686" eccentricity="0.99835366111586588" inclination="0.4471905153165035" prograde="true" rightAscensionOfAscendingNode="3.6795015113401059" semiMajorAxis="638843.79024608945" time="32116510960.447224" trueAnomaly="3.1415926535897931" />
    </Craft>
    <Craft id="444" name="Airplane-444" parent="Droo" position="589759.474691492,552050.323832276,-988543.500331287" velocity="123.003184032949,1E-09,73.3830055797664" heading="0.703845022349937,0.678175359875491,-0.0195202306831379,0.210474107048028" inContactWithPlanet="true" hasCommandPod="false" craftMass="58.0941849" craftPartCount="9" allowPlayerControl="true" waterDepth="0" initialNodes="441" surfacePosition="311291.329470893,552050.323832276,-1108211.26065018" surfaceVelocity="137.893288050003,0,38.7335758860764" surfaceRotation="0.695148767496604,0.699982008025595,-0.112013713915564,0.119358215177723">
      <InitialCrafts>
        <InitialCraft nodeId="441" name="Airplane" launchPlanetName="Droo" launchLocationName="Juno Village Runway" launchLocationType="SurfaceLockedGround" launchTime="32116319013.622425" launchMass="28712.4355" launchPrice="28580974" initialCrewCount="2" />
      </InitialCrafts>
      <Orbit argumentOfPeriapsis="4.7123889803715686" eccentricity="0.99835365045636271" inclination="0.44718217069758653" prograde="true" rightAscensionOfAscendingNode="3.6795042423041711" semiMajorAxis="638842.81664910587" time="32116510960.447224" trueAnomaly="3.1415926535897931" />
    </Craft>
    <Craft id="447" name="Airplane-447" parent="Droo" position="382326.079672975,-955711.299549266,-750432.057732619" velocity="93.5790096226674,1E-09,47.6761293977951" heading="0.145489555165741,-0.865734658752499,-0.47635668729931,-0.0491954418502458" inContactWithPlanet="true" hasCommandPod="true" craftMass="1.19999993" craftPartCount="2" allowPlayerControl="true" waterDepth="0" initialNodes="446" surfacePosition="173199.145022786,-955711.299549266,-824210.871460875" surfaceVelocity="102.779240674478,0,21.5979638552434" surfaceRotation="0.0815093539561125,-0.864675928473932,-0.491364571888547,0.0652094261893563">
      <InitialCrafts>
        <InitialCraft nodeId="446" name="Airplane" launchPlanetName="Droo" launchLocationName="Ali 28R" launchLocationType="SurfaceLockedGround" launchTime="32116319673.588169" launchMass="28712.4355" launchPrice="28580974" initialCrewCount="2" />
      </InitialCrafts>
      <Orbit argumentOfPeriapsis="1.5707963268004379" eccentricity="0.99911674828621722" inclination="0.84844234601076463" prograde="true" rightAscensionOfAscendingNode="0.47119853581270787" semiMajorAxis="637208.71777961927" time="32116510960.447224" trueAnomaly="3.1415926535897931" />
    </Craft>
    <Craft id="451" name="Airplane" parent="Droo" position="27460.7582154146,917334.572694158,883918.364467376" velocity="-110.195480538431,1E-09,3.42345127009628" heading="-0.303000645927489,0.172922577915739,0.319474888274081,0.881035956970271" inContactWithPlanet="true" hasCommandPod="true" craftMass="140.2388" craftPartCount="37" allowPlayerControl="true" waterDepth="0" initialNodes="451" surfacePosition="257224.242144351,917334.572694158,846109.601374261" surfaceVelocity="-105.481974195432,0,32.067383265999" surfaceRotation="-0.258303425908714,0.287408566327076,0.356585117560482,0.850601513031994">
      <InitialCrafts>
        <InitialCraft nodeId="451" name="Airplane" launchPlanetName="Droo" launchLocationName="Ali 28R" launchLocationType="SurfaceLockedGround" launchTime="32116323212.390224" launchMass="28712.4355" launchPrice="28580974" initialCrewCount="2" />
      </InitialCrafts>
      <Orbit argumentOfPeriapsis="4.712388980378627" eccentricity="0.999026425480392" inclination="0.80370667171780519" prograde="true" rightAscensionOfAscendingNode="6.2521282212315556" semiMajorAxis="637406.91602277092" time="32116510960.447224" trueAnomaly="3.1415926535897931" />
    </Craft>
  </Nodes>
  <MapView>
    <MapOptions gizmoAlignment="ReferenceOrbit" maneuverNodeSensitivityLinear="0.49895045161247253" orbitUiVerbosity="High" fontSize="Small" version="2" />
    <ManeuverNodes>
      <NodeChain craftId="145" />
      <NodeChain craftId="245" />
      <NodeChain craftId="261" />
      <NodeChain craftId="288" />
      <NodeChain craftId="295" />
      <NodeChain craftId="314" />
      <NodeChain craftId="335" />
      <NodeChain craftId="351" />
      <NodeChain craftId="352" />
      <NodeChain craftId="354" />
      <NodeChain craftId="355" />
      <NodeChain craftId="356" />
      <NodeChain craftId="376" />
      <NodeChain craftId="380" />
      <NodeChain craftId="411">
        <Node type="SoiEnterNodeScript" nuOnPrev="4.0890529150144745">
          <Node type="SoiExitNodeScript" nuOnPrev="1.1244560560956856" />
        </Node>
      </NodeChain>
      <NodeChain craftId="451" />
      <NodeChain craftId="458" />
    </ManeuverNodes>
    <MapItems>
      <StructureDefaults showOrbitLines="false" showIcons="true" />
      <CraftDefaults showOrbitLines="true" showIcons="true" />
      <PlanetDefaults showOrbitLines="true" showIcons="true" showSpheresOfInfluence="true" />
      <MapItem id="261" type="Craft" showOrbit="true" />
    </MapItems>
  </MapView>
</FlightState>